pypelines/__init__.py
pypelines/errors.py
pypelines/extract.py
pypelines/load.py
pypelines/pipeline.py
pypelines/py.typed
pypelines/transform.py
pypelines_etl-0.1.0.dist-info/WHEEL
pypelines_etl-0.1.0.dist-info/METADATA
pypelines_etl-0.1.0.dist-info/RECORD
