Metadata-Version: 2.1
Name: pypelines-etl
Version: 0.1.0
Summary: Simple library to make pipelines or ETL
Home-page: https://github.com/gacou54/pypelines
License: MIT
Keywords: pipeline,etl
Author: Gabriel Couture
Author-email: gacou54@gmail.com
Requires-Python: >=3.6,<4.0
Classifier: License :: OSI Approved :: MIT License
Classifier: Operating System :: OS Independent
Classifier: Programming Language :: Python :: 3
Classifier: Programming Language :: Python :: 3.6
Classifier: Programming Language :: Python :: 3.7
Classifier: Programming Language :: Python :: 3.8
Project-URL: Repository, https://github.com/gacou54/pypelines
